frst/__init__.py
frst/frst.py
frst-1.0.0.dist-info/DESCRIPTION.rst
frst-1.0.0.dist-info/METADATA
frst-1.0.0.dist-info/RECORD
frst-1.0.0.dist-info/WHEEL
frst-1.0.0.dist-info/metadata.json
frst-1.0.0.dist-info/top_level.txt
