Metadata-Version: 2.0
Name: frst
Version: 1.0.0
Summary: Fast Radial Symmetry Transform
Home-page: https://github.com/rohern/frst_python
Author: Michael Solomentsev; Ryan O'Hern
Author-email: mys29@cornell.com
License: UNKNOWN
Keywords: image processing,radial transform
Platform: UNKNOWN
Classifier: Programming Language :: Python :: 2
Classifier: License :: OSI Approved :: GNU General Public License (GPL)
Classifier: Operating System :: OS Independent
